worms/__init__.py
worms/__main__.py
worms/criteria.py
worms/criteria_unbounded.py
worms/database.py
worms/filter.py
worms/search.py
worms/util.py
worms/vis.py
worms/worms.py
worms/data/1coi.pdb
worms/data/1coi_A.pdb
worms/data/1coi_B.pdb
worms/data/1coi_C.pdb
worms/data/3uc7A.pdb
worms/data/3uc7A_clean.pdb
worms/data/__init__.py
worms/data/c1.pdb
worms/data/c2.pdb
worms/data/c3.pdb
worms/data/c3_splay.pdb
worms/data/c3het.pdb
worms/data/c4.pdb
worms/data/c5.pdb
worms/data/c6.pdb
worms/data/curved_helix.pdb
worms/data/db_asu.pdb
worms/data/hetC2A.pdb
worms/data/hetC2B.pdb
worms/data/loop.pdb
worms/data/small.pdb
worms/data/strand.pdb
worms/rosetta_symdef/C10.sym
worms/rosetta_symdef/C11.sym
worms/rosetta_symdef/C12.sym
worms/rosetta_symdef/C13.sym
worms/rosetta_symdef/C14.sym
worms/rosetta_symdef/C15.sym
worms/rosetta_symdef/C16.sym
worms/rosetta_symdef/C17.sym
worms/rosetta_symdef/C18.sym
worms/rosetta_symdef/C19.sym
worms/rosetta_symdef/C2.sym
worms/rosetta_symdef/C20.sym
worms/rosetta_symdef/C21.sym
worms/rosetta_symdef/C22.sym
worms/rosetta_symdef/C23.sym
worms/rosetta_symdef/C24.sym
worms/rosetta_symdef/C25.sym
worms/rosetta_symdef/C26.sym
worms/rosetta_symdef/C27.sym
worms/rosetta_symdef/C28.sym
worms/rosetta_symdef/C29.sym
worms/rosetta_symdef/C3.sym
worms/rosetta_symdef/C30.sym
worms/rosetta_symdef/C31.sym
worms/rosetta_symdef/C32.sym
worms/rosetta_symdef/C33.sym
worms/rosetta_symdef/C34.sym
worms/rosetta_symdef/C35.sym
worms/rosetta_symdef/C36.sym
worms/rosetta_symdef/C37.sym
worms/rosetta_symdef/C38.sym
worms/rosetta_symdef/C39.sym
worms/rosetta_symdef/C4.sym
worms/rosetta_symdef/C40.sym
worms/rosetta_symdef/C41.sym
worms/rosetta_symdef/C42.sym
worms/rosetta_symdef/C43.sym
worms/rosetta_symdef/C44.sym
worms/rosetta_symdef/C45.sym
worms/rosetta_symdef/C46.sym
worms/rosetta_symdef/C47.sym
worms/rosetta_symdef/C48.sym
worms/rosetta_symdef/C49.sym
worms/rosetta_symdef/C5.sym
worms-0.1.26.dist-info/METADATA
worms-0.1.26.dist-info/RECORD
worms-0.1.26.dist-info/WHEEL
worms-0.1.26.dist-info/top_level.txt
worms-0.1.26.dist-info/zip-safe
