Metadata-Version: 2.1
Name: worms
Version: 0.1.26
Summary: Protion Origami via Genetic Fusions
Home-page: https://github.com/willsheffler/worms
Author: Will Sheffler
Author-email: willsheffler@gmail.com
License: Apache Software License 2.0
Keywords: worms
Platform: UNKNOWN
Classifier: Development Status :: 2 - Pre-Alpha
Classifier: Intended Audience :: Developers
Classifier: License :: OSI Approved :: Apache Software License
Classifier: Natural Language :: English
Classifier: Programming Language :: Python :: 3.5
Classifier: Programming Language :: Python :: 3.6
Requires-Dist: numpy
Requires-Dist: homog (>=0.1.10)
Requires-Dist: tqdm
